instater/__init__.py
instater/cli.py
instater/context.py
instater/exceptions.py
instater/main.py
instater/util.py
instater/tasks/__init__.py
instater/tasks/_task.py
instater/tasks/command.py
instater/tasks/copy.py
instater/tasks/debug.py
instater/tasks/file.py
instater/tasks/git.py
instater/tasks/group.py
instater/tasks/pacman.py
instater/tasks/service.py
instater/tasks/user.py
instater-0.13.1.dist-info/LICENSE
instater-0.13.1.dist-info/METADATA
instater-0.13.1.dist-info/WHEEL
instater-0.13.1.dist-info/entry_points.txt
instater-0.13.1.dist-info/top_level.txt
instater-0.13.1.dist-info/RECORD
