Metadata-Version: 2.1
Name: instater
Version: 0.13.1
Summary: An easy solution for system/dotfile configuration
Home-page: https://github.com/nayaverdier/instater
Author: Naya Verdier
License: MIT
Classifier: Programming Language :: Python
Classifier: Programming Language :: Python :: 3
Requires-Python: >=3.7
License-File: LICENSE
Requires-Dist: Jinja2 ~=3.0
Requires-Dist: PyYAML ~=6.0
Requires-Dist: passlib ~=1.7
Requires-Dist: rich >=10.12.0
Requires-Dist: importlib-metadata >=1.0.0 ; python_version < "3.8"
Provides-Extra: dev
Requires-Dist: black ==23.3.0 ; extra == 'dev'
Requires-Dist: coverage ==7.2.3 ; extra == 'dev'
Requires-Dist: mypy ==1.2.0 ; extra == 'dev'
Requires-Dist: pytest ==7.3.1 ; extra == 'dev'
Requires-Dist: pytest-cov ==4.0.0 ; extra == 'dev'
Requires-Dist: twine ==4.0.2 ; extra == 'dev'
Requires-Dist: flake8 ==5.0.4 ; (python_version < "3.8") and extra == 'dev'
Requires-Dist: flake8-bugbear ==23.3.12 ; (python_version < "3.8") and extra == 'dev'
Requires-Dist: isort ==5.11.5 ; (python_version < "3.8") and extra == 'dev'
Requires-Dist: flake8 ==6.0.0 ; (python_version >= "3.8") and extra == 'dev'
Requires-Dist: flake8-bugbear ==23.3.23 ; (python_version >= "3.8") and extra == 'dev'
Requires-Dist: isort ==5.12.0 ; (python_version >= "3.8") and extra == 'dev'
